odoo_controller/__init__.py
odoo_controller/__main__.py
odoo_controller/app.py
odoo_controller/data/__init__.py
odoo_controller/data/controller.py
odoo_controller/data/query.py
odoo_controller_crossuite-1.0.0.dist-info/LICENSE
odoo_controller_crossuite-1.0.0.dist-info/METADATA
odoo_controller_crossuite-1.0.0.dist-info/WHEEL
odoo_controller_crossuite-1.0.0.dist-info/top_level.txt
odoo_controller_crossuite-1.0.0.dist-info/RECORD
