Metadata-Version: 2.1
Name: odoo-controller-crossuite
Version: 1.0.0
Summary: A basic controller to ease querying Odoo databases.
Home-page: https://gitlab.com/crossuite-projects/odoo_controller
Author: Tom Roels
Author-email: tom@crossuite.com
License: UNKNOWN
Platform: UNKNOWN
Classifier: Programming Language :: Python :: 3
Classifier: License :: OSI Approved :: GNU General Public License (GPL)
Classifier: Operating System :: OS Independent
Requires-Python: >=3.7
